Metadata-Version: 1.0
Name: python_slack_print
Version: 1.0.4
Summary: Python print for stdout and slack
Home-page: https://github.com/tacchan7412/python_slack_print
Author: Tatsuki Koga
Author-email: tacchan.04@gmail.com
License: MIT
Platform: UNKNOWN
